[1,["cdBnMv4RBNfKfuNFNrGBWF@6c48a"],["_textureSource"],["cc.SpriteFrame"],0,[{"name":"flower4","rect":{"x":3,"y":0,"width":59,"height":103},"offset":{"x":-7,"y":4},"originalSize":{"width":79,"height":111},"rotated":false,"capInsets":[0,0,0,0],"vertices":{"rawPosition":[-29.5,-51.5,0,29.5,-51.5,0,-29.5,51.5,0,29.5,51.5,0],"indexes":[0,1,2,2,1,3],"uv":[3,111,62,111,3,8,62,8],"nuv":[0.0379746835443038,0.07207207207207207,0.7848101265822784,0.07207207207207207,0.0379746835443038,1,0.7848101265822784,1],"minPos":{"x":-29.5,"y":-51.5,"z":0},"maxPos":{"x":29.5,"y":51.5,"z":0}},"packable":true,"pixelsToUnit":100,"pivot":{"x":0.5,"y":0.5},"meshType":0}],[0],0,[0],[0],[0]]
