[1,["25Ec/Lj+5L2KsKCnXE84GK@6c48a"],["_textureSource"],["cc.SpriteFrame"],0,[{"name":"btn_space","rect":{"x":0,"y":0,"width":554,"height":900},"offset":{"x":0,"y":0},"originalSize":{"width":554,"height":900},"rotated":false,"capInsets":[0,0,0,0],"vertices":{"rawPosition":[-277,-450,0,277,-450,0,-277,450,0,277,450,0],"indexes":[0,1,2,2,1,3],"uv":[0,900,554,900,0,0,554,0],"nuv":[0,0,1,0,0,1,1,1],"minPos":{"x":-277,"y":-450,"z":0},"maxPos":{"x":277,"y":450,"z":0}},"packable":true,"pixelsToUnit":100,"pivot":{"x":0.5,"y":0.5},"meshType":0}],[0],0,[0],[0],[0]]
